odoo/addons/l10n_ro_account_bank_statement_import_mt940_rffsn/README.rst
odoo/addons/l10n_ro_account_bank_statement_import_mt940_rffsn/__init__.py
odoo/addons/l10n_ro_account_bank_statement_import_mt940_rffsn/__manifest__.py
odoo/addons/l10n_ro_account_bank_statement_import_mt940_rffsn/i18n/l10n_ro_account_bank_statement_import_mt940_rffsn.pot
odoo/addons/l10n_ro_account_bank_statement_import_mt940_rffsn/i18n/ro.po
odoo/addons/l10n_ro_account_bank_statement_import_mt940_rffsn/models/__init__.py
odoo/addons/l10n_ro_account_bank_statement_import_mt940_rffsn/models/account_bank_statement_import.py
odoo/addons/l10n_ro_account_bank_statement_import_mt940_rffsn/models/account_journal.py
odoo/addons/l10n_ro_account_bank_statement_import_mt940_rffsn/models/mt940.py
odoo/addons/l10n_ro_account_bank_statement_import_mt940_rffsn/readme/CONTRIBUTORS.md
odoo/addons/l10n_ro_account_bank_statement_import_mt940_rffsn/readme/DESCRIPTION.md
odoo/addons/l10n_ro_account_bank_statement_import_mt940_rffsn/static/description/icon.png
odoo/addons/l10n_ro_account_bank_statement_import_mt940_rffsn/static/description/icon.svg
odoo/addons/l10n_ro_account_bank_statement_import_mt940_rffsn/static/description/index.html
odoo/addons/l10n_ro_account_bank_statement_import_mt940_rffsn/test_files/test_rffsn_940.txt
odoo/addons/l10n_ro_account_bank_statement_import_mt940_rffsn/tests/__init__.py
odoo/addons/l10n_ro_account_bank_statement_import_mt940_rffsn/tests/test_import_bank_statement.py
odoo_addon_l10n_ro_account_bank_statement_import_mt940_rffsn-17.0.0.1.0.dist-info/METADATA
odoo_addon_l10n_ro_account_bank_statement_import_mt940_rffsn-17.0.0.1.0.dist-info/WHEEL
odoo_addon_l10n_ro_account_bank_statement_import_mt940_rffsn-17.0.0.1.0.dist-info/top_level.txt
odoo_addon_l10n_ro_account_bank_statement_import_mt940_rffsn-17.0.0.1.0.dist-info/RECORD
